{
	"$schema": "http://json-schema.org/draft-04/schema#",
	"title": "Final Exam",
	"description": "Semesterly Final Exam JSON definition",
	"type": "object",
	"properties": {
		"kind": {
			"enum": [ "final_exam" ]
		},
		"course": {
			"allOf": [
				{
					"$ref": "course.json#/"
				}
			],
			"properties": {
				"code": {}
			},
			"additionalProperties": false
		},
		"section": {
			"allOf": [
				{
					"$ref": "section.json#/"
				}
			],
			"properties": {
				"code": {}
			},
			"additionalProperties": false
		},
		"meeting": {
			"allOf": [
				{
					"$ref": "meeting.json#/"
				}
			],
			"properties": {
				"time": {},
				"dates": {},
				"location": {}
			},
			"additionalProperties": false
		}
	},
	"required": [ "meeting" ]
}
